diffcapanalyzer/__init__.py
diffcapanalyzer/app_helper_functions.py
diffcapanalyzer/chachifuncs.py
diffcapanalyzer/databasefuncs.py
diffcapanalyzer/databasewrappers.py
diffcapanalyzer/descriptors.py
tests/__init__.py
tests/test_app_helper_functions.py
tests/test_chachifuncs.py
tests/test_databasefuncs.py
tests/test_databasewrappers.py
tests/test_descriptors.py
DiffCapAnalyzer-0.1.1.dist-info/LICENSE
DiffCapAnalyzer-0.1.1.dist-info/METADATA
DiffCapAnalyzer-0.1.1.dist-info/WHEEL
DiffCapAnalyzer-0.1.1.dist-info/top_level.txt
DiffCapAnalyzer-0.1.1.dist-info/RECORD
