Metadata-Version: 2.1
Name: DiffCapAnalyzer
Version: 0.1.1
Summary: A package for the quantitative analysis of differential capacity data!
Home-page: UNKNOWN
Author: Nicole Thompson
Author-email: nicole.thompson140@gmail.com
License: UNKNOWN
Download-URL: https://github.com/nicolet5/DiffCapAnalyzer/archive/v0.1.1.tar.gz
Platform: UNKNOWN
Classifier: Programming Language :: Python :: 3
Classifier: License :: OSI Approved :: MIT License
Classifier: Operating System :: OS Independent
Requires-Python: >=3.6
Requires-Dist: asteval (>=0.9.18)
Requires-Dist: atomicwrites (>=1.3.0)
Requires-Dist: attrs (>=19.3.0)
Requires-Dist: certifi (>=2019.11.28)
Requires-Dist: chardet (>=3.0.4)
Requires-Dist: Click (>=7.0)
Requires-Dist: colorama (>=0.4.3)
Requires-Dist: coverage (>=5.0.3)
Requires-Dist: cycler (>=0.10.0)
Requires-Dist: dash (>=1.8.0)
Requires-Dist: dash-core-components (>=1.7.0)
Requires-Dist: dash-html-components (>=1.0.2)
Requires-Dist: dash-renderer (>=1.2.3)
Requires-Dist: dash-table (>=4.6.0)
Requires-Dist: dash-table-experiments (>=0.6.0)
Requires-Dist: Flask (>=1.1.1)
Requires-Dist: Flask-Compress (>=1.4.0)
Requires-Dist: future (>=0.18.2)
Requires-Dist: idna (>=2.8)
Requires-Dist: itsdangerous (>=1.1.0)
Requires-Dist: Jinja2 (>=2.10.3)
Requires-Dist: kiwisolver (>=1.1.0)
Requires-Dist: lmfit (>=1.0.0)
Requires-Dist: MarkupSafe (>=1.1.1)
Requires-Dist: matplotlib (>=3.1.2)
Requires-Dist: more-itertools (>=8.1.0)
Requires-Dist: numpy (>=1.18.1)
Requires-Dist: packaging (>=20.1)
Requires-Dist: pandas (>=0.25.3)
Requires-Dist: PeakUtils (>=1.3.3)
Requires-Dist: plotly (>=4.5.0)
Requires-Dist: pluggy (>=0.13.1)
Requires-Dist: py (>=1.8.1)
Requires-Dist: pyparsing (>=2.4.6)
Requires-Dist: pytest (>=5.3.4)
Requires-Dist: pytest-cov (>=2.8.1)
Requires-Dist: python-dateutil (>=2.8.1)
Requires-Dist: pytz (>=2019.3)
Requires-Dist: requests (>=2.22.0)
Requires-Dist: retrying (>=1.3.3)
Requires-Dist: scipy (>=1.4.1)
Requires-Dist: six (>=1.14.0)
Requires-Dist: ua-parser (>=0.8.0)
Requires-Dist: uncertainties (>=3.1.2)
Requires-Dist: urllib3 (>=1.25.8)
Requires-Dist: wcwidth (>=0.1.8)
Requires-Dist: Werkzeug (>=0.16.0)
Requires-Dist: wincertstore (>=0.2)
